{
"type": "FeatureCollection",
"name": "WH-1001_Bedrock",
"crs": { "type": "name", "properties": { "name": "urn:ogc:def:crs:OGC:1.3:CRS84" } },
"features": [
{ "type": "Feature", "properties": { "name": "WH-1001 Bedrock", "Description": "" }, "geometry": { "type": "Point", "coordinates": [ 14.445758, 35.827119 ] } }
]
}
