{
"type": "FeatureCollection",
"name": "WH-1002_Transverse_megalith",
"crs": { "type": "name", "properties": { "name": "urn:ogc:def:crs:OGC:1.3:CRS84" } },
"features": [
{ "type": "Feature", "properties": { "name": "WH-1002 Transverse megalith", "Description": "" }, "geometry": { "type": "Point", "coordinates": [ 14.44590154489325, 35.826974289392652 ] } }
]
}
